{
  "info": {
    "_postman_id": "1b45ebcb-8f8f-4869-8bc4-a35dfaefb6e3",
    "name": "Project-Hotel-Management",
    "schema": "https://schema.getpostman.com/json/collection/v2.1.0/collection.json",
    "_exporter_id": "55022572",
    "_collection_link": "https://go.postman.co/collection/55022572-1b45ebcb-8f8f-4869-8bc4-a35dfaefb6e3?source=collection_link"
  },
  "item": [
    {
      "name": "1. Auth & Security",
      "item": [
        {
          "name": "1.1 Register",
          "item": [
            {
              "name": "1.1.1 Register - Sukses",
              "request": {
                "method": "POST",
                "header": [],
                "body": {
                  "mode": "raw",
                  "raw": "{\r\n  \"name\": \"Ricky prakusa\",\r\n  \"email\": \"rickyprakusa281@gmail.com\",\r\n  \"password\": \"Password123!\",\r\n  \"role\": \"Customer\",\r\n  \"phone\": \"08123456789\"\r\n}",
                  "options": {
                    "raw": {
                      "language": "json"
                    }
                  }
                },
                "url": {
                  "raw": "http://localhost:3000/api/v1/auth/register",
                  "protocol": "http",
                  "host": [
                    "localhost"
                  ],
                  "port": "3000",
                  "path": [
                    "api",
                    "v1",
                    "auth",
                    "register"
                  ]
                }
              },
              "response": []
            },
            {
              "name": "1.1.2  Role salah - Error",
              "request": {
                "method": "POST",
                "header": [],
                "body": {
                  "mode": "raw",
                  "raw": "{\r\n  \"name\": \"Ricky prakusa\",\r\n  \"email\": \"rickyprakusa281@gmail.com\",\r\n  \"password\": \"Password123!\",\r\n  \"role\": \"Penjual\",\r\n  \"phone\": \"08123456789\"\r\n}",
                  "options": {
                    "raw": {
                      "language": "json"
                    }
                  }
                },
                "url": {
                  "raw": "http://localhost:3000/api/v1/auth/register",
                  "protocol": "http",
                  "host": [
                    "localhost"
                  ],
                  "port": "3000",
                  "path": [
                    "api",
                    "v1",
                    "auth",
                    "register"
                  ]
                }
              },
              "response": []
            },
            {
              "name": "1.1.3 Email Kembar - Error",
              "request": {
                "method": "POST",
                "header": [],
                "body": {
                  "mode": "raw",
                  "raw": "{\r\n  \"name\": \"Ricky prakusa\",\r\n  \"email\": \"rickyprakusa281@gmail.com\",\r\n  \"password\": \"Password123!\",\r\n  \"role\": \"Customer\",\r\n  \"phone\": \"08123456789\"\r\n}",
                  "options": {
                    "raw": {
                      "language": "json"
                    }
                  }
                },
                "url": {
                  "raw": "http://localhost:3000/api/v1/auth/register",
                  "protocol": "http",
                  "host": [
                    "localhost"
                  ],
                  "port": "3000",
                  "path": [
                    "api",
                    "v1",
                    "auth",
                    "register"
                  ]
                }
              },
              "response": []
            },
            {
              "name": "1.1.4 Data tidak lengkap - Error",
              "request": {
                "method": "POST",
                "header": [],
                "body": {
                  "mode": "raw",
                  "raw": "{\r\n  \"name\": \"\",\r\n  \"email\": \"\",\r\n  \"password\": \"\",\r\n  \"role\": \"\",\r\n  \"phone\": \"\"\r\n}",
                  "options": {
                    "raw": {
                      "language": "json"
                    }
                  }
                },
                "url": {
                  "raw": "http://localhost:3000/api/v1/auth/register",
                  "protocol": "http",
                  "host": [
                    "localhost"
                  ],
                  "port": "3000",
                  "path": [
                    "api",
                    "v1",
                    "auth",
                    "register"
                  ]
                }
              },
              "response": []
            },
            {
              "name": "1.1.5 Format email salah - Error",
              "request": {
                "method": "POST",
                "header": [],
                "body": {
                  "mode": "raw",
                  "raw": "{\r\n  \"name\": \"Ricky prakusa\",\r\n  \"email\": \"rickyprakusa281\",\r\n  \"password\": \"Password123!\",\r\n  \"role\": \"Customer\",\r\n  \"phone\": \"08123456789\"\r\n}",
                  "options": {
                    "raw": {
                      "language": "json"
                    }
                  }
                },
                "url": {
                  "raw": "http://localhost:3000/api/v1/auth/register",
                  "protocol": "http",
                  "host": [
                    "localhost"
                  ],
                  "port": "3000",
                  "path": [
                    "api",
                    "v1",
                    "auth",
                    "register"
                  ]
                }
              },
              "response": []
            },
            {
              "name": "1.1.6 Nama minimal 2 karakter - Error",
              "request": {
                "method": "POST",
                "header": [],
                "body": {
                  "mode": "raw",
                  "raw": "{\r\n  \"name\": \"R\",\r\n  \"email\": \"rickyprakusa281@gmail.com\",\r\n  \"password\": \"Password123!\",\r\n  \"role\": \"Customer\",\r\n  \"phone\": \"08123456789\"\r\n}",
                  "options": {
                    "raw": {
                      "language": "json"
                    }
                  }
                },
                "url": {
                  "raw": "http://localhost:3000/api/v1/auth/register",
                  "protocol": "http",
                  "host": [
                    "localhost"
                  ],
                  "port": "3000",
                  "path": [
                    "api",
                    "v1",
                    "auth",
                    "register"
                  ]
                }
              },
              "response": []
            }
          ]
        },
        {
          "name": "1.2 Login",
          "item": [
            {
              "name": "1.2.1 Belum terverifikasi OTP - Error",
              "request": {
                "auth": {
                  "type": "noauth"
                },
                "method": "POST",
                "header": [],
                "body": {
                  "mode": "raw",
                  "raw": "{\r\n  \"email\": \"rickyprakusa281@gmail.com\",\r\n  \"password\": \"Password123!\"\r\n}",
                  "options": {
                    "raw": {
                      "language": "json"
                    }
                  }
                },
                "url": {
                  "raw": "http://localhost:3000/api/v1/auth/login",
                  "protocol": "http",
                  "host": [
                    "localhost"
                  ],
                  "port": "3000",
                  "path": [
                    "api",
                    "v1",
                    "auth",
                    "login"
                  ]
                }
              },
              "response": []
            },
            {
              "name": "1.2.2 Email tidak terdaftar - Error",
              "request": {
                "auth": {
                  "type": "noauth"
                },
                "method": "POST",
                "header": [],
                "body": {
                  "mode": "raw",
                  "raw": "{\r\n  \"email\": \"rickyprakusa2@gmail.com\",\r\n  \"password\": \"Password123!\"\r\n}",
                  "options": {
                    "raw": {
                      "language": "json"
                    }
                  }
                },
                "url": {
                  "raw": "http://localhost:3000/api/v1/auth/login",
                  "protocol": "http",
                  "host": [
                    "localhost"
                  ],
                  "port": "3000",
                  "path": [
                    "api",
                    "v1",
                    "auth",
                    "login"
                  ]
                }
              },
              "response": []
            },
            {
              "name": "1.2.3 Data tidak lengkap - Error",
              "request": {
                "auth": {
                  "type": "noauth"
                },
                "method": "POST",
                "header": [],
                "body": {
                  "mode": "raw",
                  "raw": "{\r\n  \"email\": \"\",\r\n  \"password\": \"\"\r\n}",
                  "options": {
                    "raw": {
                      "language": "json"
                    }
                  }
                },
                "url": {
                  "raw": "http://localhost:3000/api/v1/auth/login",
                  "protocol": "http",
                  "host": [
                    "localhost"
                  ],
                  "port": "3000",
                  "path": [
                    "api",
                    "v1",
                    "auth",
                    "login"
                  ]
                }
              },
              "response": []
            },
            {
              "name": "1.2.2 Email tidak terdaftar - Error Copy",
              "request": {
                "auth": {
                  "type": "noauth"
                },
                "method": "POST",
                "header": [],
                "body": {
                  "mode": "raw",
                  "raw": "{\r\n  \"email\": \"rickyprakusa281@gmail.com\",\r\n  \"password\": \"Password123=dg!\"\r\n}",
                  "options": {
                    "raw": {
                      "language": "json"
                    }
                  }
                },
                "url": {
                  "raw": "http://localhost:3000/api/v1/auth/login",
                  "protocol": "http",
                  "host": [
                    "localhost"
                  ],
                  "port": "3000",
                  "path": [
                    "api",
                    "v1",
                    "auth",
                    "login"
                  ]
                }
              },
              "response": []
            }
          ]
        },
        {
          "name": "1.3 Verifikasi Token",
          "item": [
            {
              "name": "1.3.1 OTP salah - Error",
              "request": {
                "auth": {
                  "type": "noauth"
                },
                "method": "POST",
                "header": [],
                "body": {
                  "mode": "raw",
                  "raw": "{\r\n  \"email\": \"rickyprakusa281@gmail.com\",\r\n  \"otpCode\": \"763080\"\r\n}",
                  "options": {
                    "raw": {
                      "language": "json"
                    }
                  }
                },
                "url": {
                  "raw": "http://localhost:3000/api/v1/auth/verify-otp",
                  "protocol": "http",
                  "host": [
                    "localhost"
                  ],
                  "port": "3000",
                  "path": [
                    "api",
                    "v1",
                    "auth",
                    "verify-otp"
                  ]
                }
              },
              "response": []
            },
            {
              "name": "1.3.2 OTP kedaluwarsa - Error",
              "request": {
                "auth": {
                  "type": "noauth"
                },
                "method": "POST",
                "header": [],
                "body": {
                  "mode": "raw",
                  "raw": "{\r\n  \"email\": \"rickyprakusa281@gmail.com\",\r\n  \"otpCode\": \"397229\"\r\n}",
                  "options": {
                    "raw": {
                      "language": "json"
                    }
                  }
                },
                "url": {
                  "raw": "http://localhost:3000/api/v1/auth/verify-otp",
                  "protocol": "http",
                  "host": [
                    "localhost"
                  ],
                  "port": "3000",
                  "path": [
                    "api",
                    "v1",
                    "auth",
                    "verify-otp"
                  ]
                }
              },
              "response": []
            },
            {
              "name": "1.3.3 Email Tidak terdaftar - Error",
              "request": {
                "auth": {
                  "type": "noauth"
                },
                "method": "POST",
                "header": [],
                "body": {
                  "mode": "raw",
                  "raw": "{\r\n  \"email\": \"rickyprakusa28@gmail.com\",\r\n  \"otpCode\": \"763080\"\r\n}",
                  "options": {
                    "raw": {
                      "language": "json"
                    }
                  }
                },
                "url": {
                  "raw": "http://localhost:3000/api/v1/auth/verify-otp",
                  "protocol": "http",
                  "host": [
                    "localhost"
                  ],
                  "port": "3000",
                  "path": [
                    "api",
                    "v1",
                    "auth",
                    "verify-otp"
                  ]
                }
              },
              "response": []
            },
            {
              "name": "1.3.4 Data tidak lengkap - Error",
              "request": {
                "auth": {
                  "type": "noauth"
                },
                "method": "POST",
                "header": [],
                "body": {
                  "mode": "raw",
                  "raw": "{\r\n  \"email\": \"\",\r\n  \"otpCode\": \"\"\r\n}",
                  "options": {
                    "raw": {
                      "language": "json"
                    }
                  }
                },
                "url": {
                  "raw": "http://localhost:3000/api/v1/auth/verify-otp",
                  "protocol": "http",
                  "host": [
                    "localhost"
                  ],
                  "port": "3000",
                  "path": [
                    "api",
                    "v1",
                    "auth",
                    "verify-otp"
                  ]
                }
              },
              "response": []
            },
            {
              "name": "1.3.5 OTP benar - Sukses",
              "request": {
                "auth": {
                  "type": "noauth"
                },
                "method": "POST",
                "header": [],
                "body": {
                  "mode": "raw",
                  "raw": "{\r\n  \"email\": \"rickyprakusa281@gmail.com\",\r\n  \"otpCode\": \"888319\"\r\n}",
                  "options": {
                    "raw": {
                      "language": "json"
                    }
                  }
                },
                "url": {
                  "raw": "http://localhost:3000/api/v1/auth/verify-otp",
                  "protocol": "http",
                  "host": [
                    "localhost"
                  ],
                  "port": "3000",
                  "path": [
                    "api",
                    "v1",
                    "auth",
                    "verify-otp"
                  ]
                }
              },
              "response": []
            }
          ]
        },
        {
          "name": "1.4 Resend OTP",
          "item": [
            {
              "name": "1.4.1 Password salah -Error",
              "request": {
                "auth": {
                  "type": "noauth"
                },
                "method": "POST",
                "header": [],
                "body": {
                  "mode": "raw",
                  "raw": "{\r\n  \"email\": \"rickyprakusa281@gmail.com\",\r\n  \"password\": \"Password12!\"\r\n}",
                  "options": {
                    "raw": {
                      "language": "json"
                    }
                  }
                },
                "url": {
                  "raw": "http://localhost:3000/api/v1/auth/resend-otp",
                  "protocol": "http",
                  "host": [
                    "localhost"
                  ],
                  "port": "3000",
                  "path": [
                    "api",
                    "v1",
                    "auth",
                    "resend-otp"
                  ]
                }
              },
              "response": []
            },
            {
              "name": "1.4.2 Email tidak terdaftar -Error",
              "request": {
                "auth": {
                  "type": "noauth"
                },
                "method": "POST",
                "header": [],
                "body": {
                  "mode": "raw",
                  "raw": "{\r\n  \"email\": \"rickyprakusa28@gmail.com\",\r\n  \"password\": \"Password123!\"\r\n}",
                  "options": {
                    "raw": {
                      "language": "json"
                    }
                  }
                },
                "url": {
                  "raw": "http://localhost:3000/api/v1/auth/resend-otp",
                  "protocol": "http",
                  "host": [
                    "localhost"
                  ],
                  "port": "3000",
                  "path": [
                    "api",
                    "v1",
                    "auth",
                    "resend-otp"
                  ]
                }
              },
              "response": []
            },
            {
              "name": "1.4.3 Data tidak lengkap -Error",
              "request": {
                "auth": {
                  "type": "noauth"
                },
                "method": "POST",
                "header": [],
                "body": {
                  "mode": "raw",
                  "raw": "{\r\n  \"email\": \"\",\r\n  \"password\": \"\"\r\n}",
                  "options": {
                    "raw": {
                      "language": "json"
                    }
                  }
                },
                "url": {
                  "raw": "http://localhost:3000/api/v1/auth/resend-otp",
                  "protocol": "http",
                  "host": [
                    "localhost"
                  ],
                  "port": "3000",
                  "path": [
                    "api",
                    "v1",
                    "auth",
                    "resend-otp"
                  ]
                }
              },
              "response": []
            },
            {
              "name": "1.4.4 OTP benar -Sukses",
              "request": {
                "auth": {
                  "type": "noauth"
                },
                "method": "POST",
                "header": [],
                "body": {
                  "mode": "raw",
                  "raw": "{\r\n  \"email\": \"rickyprakusa281@gmail.com\",\r\n  \"password\": \"Password123!\"\r\n}",
                  "options": {
                    "raw": {
                      "language": "json"
                    }
                  }
                },
                "url": {
                  "raw": "http://localhost:3000/api/v1/auth/resend-otp",
                  "protocol": "http",
                  "host": [
                    "localhost"
                  ],
                  "port": "3000",
                  "path": [
                    "api",
                    "v1",
                    "auth",
                    "resend-otp"
                  ]
                }
              },
              "response": []
            },
            {
              "name": "1.4.5 Spam OTP -Error",
              "request": {
                "auth": {
                  "type": "noauth"
                },
                "method": "POST",
                "header": [],
                "body": {
                  "mode": "raw",
                  "raw": "{\r\n  \"email\": \"rickyprakusa281@gmail.com\",\r\n  \"password\": \"Password123!\"\r\n}",
                  "options": {
                    "raw": {
                      "language": "json"
                    }
                  }
                },
                "url": {
                  "raw": "http://localhost:3000/api/v1/auth/resend-otp",
                  "protocol": "http",
                  "host": [
                    "localhost"
                  ],
                  "port": "3000",
                  "path": [
                    "api",
                    "v1",
                    "auth",
                    "resend-otp"
                  ]
                }
              },
              "response": []
            },
            {
              "name": "1.4.6 Sudah diverifikasi -Error",
              "request": {
                "auth": {
                  "type": "noauth"
                },
                "method": "POST",
                "header": [],
                "body": {
                  "mode": "raw",
                  "raw": "{\r\n  \"email\": \"rickyprakusa281@gmail.com\",\r\n  \"password\": \"Password123!\"\r\n}",
                  "options": {
                    "raw": {
                      "language": "json"
                    }
                  }
                },
                "url": {
                  "raw": "http://localhost:3000/api/v1/auth/resend-otp",
                  "protocol": "http",
                  "host": [
                    "localhost"
                  ],
                  "port": "3000",
                  "path": [
                    "api",
                    "v1",
                    "auth",
                    "resend-otp"
                  ]
                }
              },
              "response": []
            }
          ]
        }
      ]
    },
    {
      "name": "http://localhost:3000/api/v1/wallets",
      "request": {
        "auth": {
          "type": "bearer",
          "bearer": [
            {
              "key": "token",
              "value": "{{supabase_service_role_api_key_0y13}}",
              "type": "string"
            }
          ]
        },
        "method": "GET",
        "header": [],
        "url": {
          "raw": "http://localhost:3000/api/v1/wallets",
          "protocol": "http",
          "host": [
            "localhost"
          ],
          "port": "3000",
          "path": [
            "api",
            "v1",
            "wallets"
          ]
        }
      },
      "response": []
    },
    {
      "name": "http://localhost:3000/api/v1/wallets/topup",
      "request": {
        "auth": {
          "type": "bearer",
          "bearer": [
            {
              "key": "token",
              "value": "{{json_web_token_0y13}}",
              "type": "string"
            }
          ]
        },
        "method": "POST",
        "header": [],
        "body": {
          "mode": "raw",
          "raw": "{\r\n  \"amount\": 100000\r\n}",
          "options": {
            "raw": {
              "language": "json"
            }
          }
        },
        "url": {
          "raw": "http://localhost:3000/api/v1/wallets/topup",
          "protocol": "http",
          "host": [
            "localhost"
          ],
          "port": "3000",
          "path": [
            "api",
            "v1",
            "wallets",
            "topup"
          ]
        }
      },
      "response": []
    }
  ],
  "variable": [
    {
      "key": "supabase_service_role_api_key_0y13",
      "secret": true
    },
    {
      "key": "json_web_token_0y13",
      "secret": true
    }
  ]
}